AUTHORS.rst
HISTORY.rst
LICENSE
MANIFEST.in
README.rst
setup.cfg
setup.py
joystick/__init__.py
joystick/_version.py
joystick/colorbarmanager.py
joystick/core.py
joystick/deco.py
joystick/example.py
joystick/frame.py
joystick/graph.py
joystick/graphmulti.py
joystick/image.py
joystick/joystick.py
joystick/scatter.py
joystick/text.py
joystick.egg-info/PKG-INFO
joystick.egg-info/SOURCES.txt
joystick.egg-info/dependency_links.txt
joystick.egg-info/top_level.txt