Metadata-Version: 1.1
Name: joystick
Version: 0.3.7
Summary: Real-time plotting and logging while console controlling
Home-page: https://github.com/ceyzeriat/joystick/
Author: Guillaume Schworer
Author-email: guillaume.schworer@gmail.com
License: GNU General Public License v3 or later (GPLv3+)
Download-URL: https://github.com/ceyzeriat/joystick/tree/master/dist
Keywords: realtime,real,time,live,stream,figure,data,matplotlib,control,thread,serial,plot
Platform: UNKNOWN
Classifier: Development Status :: 4 - Beta
Classifier: Environment :: Console
Classifier: Intended Audience :: Developers
Classifier: Intended Audience :: Education
Classifier: Intended Audience :: Science/Research
Classifier: License :: OSI Approved :: GNU General Public License v3 or later (GPLv3+)
Classifier: Operating System :: OS Independent
Classifier: Programming Language :: Python
